mcp_hive/__init__.py
mcp_hive/agent.py
mcp_hive/client.py
mcp_hive/types.py
mcp_hive-0.2.0.dist-info/METADATA
mcp_hive-0.2.0.dist-info/WHEEL
mcp_hive-0.2.0.dist-info/top_level.txt
mcp_hive-0.2.0.dist-info/RECORD
