Metadata-Version: 2.2
Name: mcp-hive
Version: 0.2.0
Summary: Python SDK for MCP Hive - The hub for all your LLM tools
Home-page: https://github.com/trilogy-group/mcp-hive
Author: Ashish Mandal
Author-email: mandal.ashish@codenation.co.in
Classifier: Programming Language :: Python :: 3
Classifier: License :: OSI Approved :: MIT License
Classifier: Operating System :: OS Independent
Requires-Python: >=3.8
Requires-Dist: rich==13.9.4
Requires-Dist: python-dotenv==1.0.1
Requires-Dist: langchain==0.3.15
Requires-Dist: langchain-anthropic==0.3.4
Requires-Dist: mcp==1.2.0
Dynamic: author
Dynamic: author-email
Dynamic: classifier
Dynamic: description
Dynamic: description-content-type
Dynamic: home-page
Dynamic: requires-dist
Dynamic: requires-python
Dynamic: summary
